[
    {
        "module": "../..",
        "size": {
            ".text": 32916,
            ".data": 473,
            ".bss": 6718,
            ".text-delta": 32916,
            ".data-delta": 473,
            ".bss-delta": 6718
        }
    },
    {
        "module": "BUILD/K66F",
        "size": {
            ".text": 358,
            ".data": 0,
            ".bss": 596,
            ".text-delta": 358,
            ".data-delta": 0,
            ".bss-delta": 596
        }
    },
    {
        "module": "[fill]",
        "size": {
            ".text": 190,
            ".data": 11,
            ".bss": 33,
            ".text-delta": 190,
            ".data-delta": 11,
            ".bss-delta": 33
        }
    },
    {
        "module": "[lib]/c.a",
        "size": {
            ".text": 35391,
            ".data": 2472,
            ".bss": 89,
            ".text-delta": 35391,
            ".data-delta": 2472,
            ".bss-delta": 89
        }
    },
    {
        "module": "[lib]/gcc.a",
        "size": {
            ".text": 3112,
            ".data": 0,
            ".bss": 0,
            ".text-delta": 3112,
            ".data-delta": 0,
            ".bss-delta": 0
        }
    },
    {
        "module": "[lib]/misc",
        "size": {
            ".text": 180,
            ".data": 4,
            ".bss": 28,
            ".text-delta": 180,
            ".data-delta": 4,
            ".bss-delta": 28
        }
    },
    {
        "module": "[lib]/nosys.a",
        "size": {
            ".text": 32,
            ".data": 0,
            ".bss": 0,
            ".text-delta": 32,
            ".data-delta": 0,
            ".bss-delta": 0
        }
    },
    {
        "summary": {
            "static_ram": 10424,
            "static_ram_delta": 10424,
            "total_flash": 75139,
            "total_flash_delta": 75139
        }
    }
]
